setup.py
probability_dist_gauss_binomial/Binomialdistribution.py
probability_dist_gauss_binomial/Gaussiandistribution.py
probability_dist_gauss_binomial/Generaldistribution.py
probability_dist_gauss_binomial/__init__.py
probability_dist_gauss_binomial.egg-info/PKG-INFO
probability_dist_gauss_binomial.egg-info/SOURCES.txt
probability_dist_gauss_binomial.egg-info/dependency_links.txt
probability_dist_gauss_binomial.egg-info/not-zip-safe
probability_dist_gauss_binomial.egg-info/top_level.txt