Metadata-Version: 1.0
Name: probability-dist-gauss-binomial
Version: 1.0
Summary: Gaussian distribution and Binomial distribution
Home-page: UNKNOWN
Author: Akhil Kumar
Author-email: akhilkumar.ganji24@gmail.com
License: UNKNOWN
Platform: UNKNOWN
